README.txt
setup.cfg
setup.py
lpp/__init__.py
lpp.egg-info/PKG-INFO
lpp.egg-info/SOURCES.txt
lpp.egg-info/dependency_links.txt
lpp.egg-info/requires.txt
lpp.egg-info/top_level.txt
lpp.egg-info/zip-safe