Metadata-Version: 1.1
Name: lpp
Version: 2.0.1
Summary:  A package for Bioinfomatics
Home-page: https://github.com/lpp1985/lpp_Script
Author: Pengpeng Li
Author-email: 409511038@qq.com
License: UNKNOWN
Keywords: Pipeline Bioinfomatics package
Platform: UNKNOWN
Classifier: Programming Language :: Python
Classifier: Intended Audience :: Developers
Classifier: Operating System :: OS Independent
Classifier: Programming Language :: Python :: 3
